LICENSE.txt
MANIFEST.in
NOTICE
README.md
setup.cfg
setup.py
superset/__init__.py
superset/app.py
superset/cli.py
superset/config.py
superset/constants.py
superset/dataframe.py
superset/exceptions.py
superset/extensions.py
superset/forms.py
superset/jinja_context.py
superset/legacy.py
superset/result_set.py
superset/sql_lab.py
superset/sql_parse.py
superset/stats_logger.py
superset/typing.py
superset/viz.py
superset.egg-info/PKG-INFO
superset.egg-info/SOURCES.txt
superset.egg-info/dependency_links.txt
superset.egg-info/not-zip-safe
superset.egg-info/top_level.txt
superset/assets/package.json
superset/bin/__init__.py
superset/bin/superset
superset/common/__init__.py
superset/common/query_context.py
superset/common/query_object.py
superset/common/tags.py
superset/connectors/__init__.py
superset/connectors/connector_registry.py
superset/connectors/base/__init__.py
superset/connectors/base/models.py
superset/connectors/base/views.py
superset/connectors/druid/__init__.py
superset/connectors/druid/models.py
superset/connectors/druid/views.py
superset/connectors/sqla/__init__.py
superset/connectors/sqla/models.py
superset/connectors/sqla/views.py
superset/db_engine_specs/__init__.py
superset/db_engine_specs/athena.py
superset/db_engine_specs/base.py
superset/db_engine_specs/bigquery.py
superset/db_engine_specs/clickhouse.py
superset/db_engine_specs/db2.py
superset/db_engine_specs/dremio.py
superset/db_engine_specs/drill.py
superset/db_engine_specs/druid.py
superset/db_engine_specs/elasticsearch.py
superset/db_engine_specs/exasol.py
superset/db_engine_specs/gsheets.py
superset/db_engine_specs/hana.py
superset/db_engine_specs/hive.py
superset/db_engine_specs/impala.py
superset/db_engine_specs/kylin.py
superset/db_engine_specs/mssql.py
superset/db_engine_specs/mysql.py
superset/db_engine_specs/oracle.py
superset/db_engine_specs/pinot.py
superset/db_engine_specs/postgres.py
superset/db_engine_specs/presto.py
superset/db_engine_specs/redshift.py
superset/db_engine_specs/snowflake.py
superset/db_engine_specs/sqlite.py
superset/db_engine_specs/teradata.py
superset/db_engine_specs/vertica.py
superset/db_engines/__init__.py
