Metadata-Version: 2.1
Name: superset
Version: 0.30.1
Summary: Superset has moved to apache-superset, as of 0.34.0 onwards, please pip install apache-superset
Home-page: https://superset.apache.org/
Author: Apache Software Foundation
Author-email: dev@superset.incubator.apache.org
License: Apache License, Version 2.0
Download-URL: https://www.apache.org/dist/incubator/superset/0.999.0dev
Platform: UNKNOWN
Classifier: Programming Language :: Python :: 3.6
Classifier: Programming Language :: Python :: 3.7
Requires-Python: ~=3.6
